guavasaurus/__init__.py
guavasaurus/qubits/__init__.py
guavasaurus/qubits/algorithms.py
guavasaurus/qubits/circuit.py
guavasaurus/qubits/gates.py
guavasaurus/qubits/quantum_language.py
guavasaurus/qubits/qubit.py
guavasaurus/qubits/simulator.py
guavasaurus/qutrits/Qutrit.py
guavasaurus/qutrits/__init__.py
guavasaurus/qutrits/circuit_qutrit.py
guavasaurus/qutrits/gates_qutrit.py
guavasaurus/qutrits/quantum_language_qutrit.py
guavasaurus/qutrits/simulator_qutrit.py
guavasaurus-1.6.dist-info/METADATA
guavasaurus-1.6.dist-info/WHEEL
guavasaurus-1.6.dist-info/top_level.txt
guavasaurus-1.6.dist-info/RECORD
